cdp_use/__init__.py
cdp_use/client.py
cdp_use/cdp/__init__.py
cdp_use/cdp/library.py
cdp_use/cdp/registration_library.py
cdp_use/cdp/registry.py
cdp_use/cdp/accessibility/__init__.py
cdp_use/cdp/accessibility/commands.py
cdp_use/cdp/accessibility/events.py
cdp_use/cdp/accessibility/library.py
cdp_use/cdp/accessibility/registration.py
cdp_use/cdp/accessibility/types.py
cdp_use/cdp/animation/__init__.py
cdp_use/cdp/animation/commands.py
cdp_use/cdp/animation/events.py
cdp_use/cdp/animation/library.py
cdp_use/cdp/animation/registration.py
cdp_use/cdp/animation/types.py
cdp_use/cdp/audits/__init__.py
cdp_use/cdp/audits/commands.py
cdp_use/cdp/audits/events.py
cdp_use/cdp/audits/library.py
cdp_use/cdp/audits/registration.py
cdp_use/cdp/audits/types.py
cdp_use/cdp/autofill/__init__.py
cdp_use/cdp/autofill/commands.py
cdp_use/cdp/autofill/events.py
cdp_use/cdp/autofill/library.py
cdp_use/cdp/autofill/registration.py
cdp_use/cdp/autofill/types.py
cdp_use/cdp/backgroundservice/__init__.py
cdp_use/cdp/backgroundservice/commands.py
cdp_use/cdp/backgroundservice/events.py
cdp_use/cdp/backgroundservice/library.py
cdp_use/cdp/backgroundservice/registration.py
cdp_use/cdp/backgroundservice/types.py
cdp_use/cdp/bluetoothemulation/__init__.py
cdp_use/cdp/bluetoothemulation/commands.py
cdp_use/cdp/bluetoothemulation/events.py
cdp_use/cdp/bluetoothemulation/library.py
cdp_use/cdp/bluetoothemulation/registration.py
cdp_use/cdp/bluetoothemulation/types.py
cdp_use/cdp/browser/__init__.py
cdp_use/cdp/browser/commands.py
cdp_use/cdp/browser/events.py
cdp_use/cdp/browser/library.py
cdp_use/cdp/browser/registration.py
cdp_use/cdp/browser/types.py
cdp_use/cdp/cachestorage/__init__.py
cdp_use/cdp/cachestorage/commands.py
cdp_use/cdp/cachestorage/events.py
cdp_use/cdp/cachestorage/library.py
cdp_use/cdp/cachestorage/registration.py
cdp_use/cdp/cachestorage/types.py
cdp_use/cdp/cast/__init__.py
cdp_use/cdp/cast/commands.py
cdp_use/cdp/cast/events.py
cdp_use/cdp/cast/library.py
cdp_use-1.4.3.dist-info/METADATA
cdp_use-1.4.3.dist-info/WHEEL
cdp_use-1.4.3.dist-info/licenses/LICENSE
cdp_use-1.4.3.dist-info/RECORD
